[
  {
    "transliteration": "Subhan Allah",
    "audio_url": "http://zj-s.usicdn.com/muslim/res/tasbih/subhanallah.mp3",
    "content_ar": "سُبْحَانَ اللهِ",
    "default_count": 33,
    "order": 1,
    "content_en": "Glory be to Allah",
    "content_ms": "Maha suci Allah",
    "content_ru": "Слава Аллаху",
    "content_ur": "سبحان اللہ",
    "content_zh-rCN": "愿荣耀归真主阿拉",
    "content_bn": "মহিমা আল্লাহর জন্য",
    "content_hi": "सुभान अल्लाह",
    "content_tr": "Allah\\'a şükürler olsun",
    "content_fr": "Gloire à Allah",
    "content_de": "Gepriesen sei Allah"
  },
  {
    "transliteration": "Alhamdulillah",
    "audio_url": "http://zj-s.usicdn.com/muslim/res/tasbih/alhamdulillah.mp3",
    "content_ar": "اَلْحَمْدُ لِله",
    "default_count": 33,
    "order": 2,
    "content_en": "Praise be to Allah",
    "content_ms": "Segala puji bagi Allah",
    "content_ru": "Хвала Аллаху",
    "content_ur": "تمام تعریف اللہ کے لیے.",
    "content_zh-rCN": "赞颂全归真主",
    "content_bn": "সমস্ত প্রশংসা মহান আল্লাহর",
    "content_hi": "Praise be to Allah",
    "content_tr": "Hamd Allah\\'a mahsustur",
    "content_fr": "Louange à Allah",
    "content_de": "Mein Lob und meine Verehrung dem Herrn"
  },
  {
    "transliteration": "Allahu Akbar",
    "audio_url": "http://zj-s.usicdn.com/muslim/res/tasbih/allahuakbar.mp3",
    "content_ar": "اللهُ أَكْبَرْ",
    "default_count": 33,
    "order": 3,
    "content_en": "Allah is The Greatest",
    "content_ms": "Allah Maha Besar",
    "content_ru": "Аллаху Акбар",
    "content_ur": "اللّه سب سے بڑا ہےالله سب سے بڑا ہے",
    "content_zh-rCN": "真主至大",
    "content_bn": "আল্লাহ সর্বশ্রেষ্ঠ",
    "content_hi": "Allah is The Greatest",
    "content_tr": "Allah en Büyüktür",
    "content_fr": "Allah est le plus grand",
    "content_de": "Allah ist der Beste."
  },
  {
    "transliteration": "La ilaha illa Allah",
    "audio_url": "http://zj-s.usicdn.com/muslim/res/tasbih/lailahaillallah.mp3",
    "content_ar": "لَا إِلَهَ إِلَّا الله",
    "default_count": 33,
    "order": 4,
    "content_en": "There is no god except Allah",
    "content_ms": "Tiada tuhan melainkan Allah",
    "content_ru": "Нет божества достойного поклонения, помимо Аллаха",
    "content_ur": "اللہ کے سوا کوئی معبود نہیں",
    "content_zh-rCN": "除真主外，没有其他神灵",
    "content_bn": "আল্লাহ ছাড়া কোনো মা\\'বুদ্ নেই",
    "content_hi": "There is no god except Allah",
    "content_tr": "Allah\\'tan başka ilah yoktur",
    "content_fr": "Il n\\'y a pas de dieu sauf Allah",
    "content_de": "Es gibt keinen Gott außer Gott"
  },
  {
    "transliteration": "Subhan Allahi wa bi Hamdihi, Subhan Allahil Adhim",
    "audio_url": "http://zj-s.usicdn.com/muslim/res/tasbih/subhanallahi_long.mp3",
    "content_ar": "سُبْحَانَ اللهِ وَ بِحَمْدِهِ, سُبْحَانَ اللهِ الْعَظِيْم",
    "default_count": 33,
    "order": 5,
    "content_en": "Allah is free from imperfections and all praise is due to Him, Allah is The Greatest",
    "content_ms": "Mahasuci Allah dan segala puji bagi-Nya. Mahasuci Allah yang Maha agung",
    "content_ru": "Пречист Аллах, хвала Ему, Пречист Аллах Всевышний",
    "content_ur": "ذکر_ترجمان_سوبناللہاہی_لگ \\\"سبحان الٰہی و دو ہمدیہی ، سبحان اللہ العظیم\\\" کا ترجمہ ، جو آپ کی زبان کے لئے بڑے پیمانے پر استعمال ہوتا ہے اسے استعمال کرنا بہتر ہوگا.",
    "content_zh-rCN": "Allah is free from imperfections and all praise is due to Him, Allah is The Greatest",
    "content_bn": "মহান আল্লাহ সকল ত্রুটির উর্দ্ধে, এবং সমস্ত প্রশংসা তার, অবশ্যই আল্লাহ সর্বশ্রেষ্ঠ",
    "content_hi": "Allah is free from imperfections and all praise is due to Him, Allah is The Greatest",
    "content_tr": "Allah noksanlardan münezzehtir, Allah en Büyüktür",
    "content_fr": "Allah est exempt d\\'imperfections et toute louange lui est due, Allah est le plus grand",
    "content_de": "Allah ist frei von Fehlern und jeder lob ist wegen ihm, Allah ist der Beste."
  },
  {
    "transliteration": "Astagfirullah",
    "audio_url": "http://zj-s.usicdn.com/muslim/res/tasbih/astagfirullah.mp3",
    "content_ar": "أَسْتَغْفِرُ الله",
    "default_count": 33,
    "order": 6,
    "content_en": "I seek Allah\\'s forgiveness",
    "content_ms": "Aku memohon keampunan Allah",
    "content_ru": "Я прошу прощения у Аллаха",
    "content_ur": "میں اللہ کی مغفرت طلب کرتا ہوں",
    "content_zh-rCN": "愿主恕饶",
    "content_bn": "আমি আল্লাহর ক্ষমা প্রার্থনা করছি",
    "content_hi": "I seek Allah\\'s forgiveness",
    "content_tr": "Allah\\'tan af dilerim",
    "content_fr": "Je cherche le pardon d\\'Allah",
    "content_de": "Ich bitte um Allahs Vergebung"
  },
  {
    "transliteration": "Astagfirullahal 'azeem",
    "audio_url": "http://zj-s.usicdn.com/muslim/res/tasbih/astagfirullah_long.mp3",
    "content_ar": "أَسْتَغْفِرُ اللهَ الْعَظِيْم",
    "default_count": 33,
    "order": 7,
    "content_en": "I seek the forgiveness of Allah the Almighty",
    "content_ms": "Aku mohon ampunan kepada Allah Yang Maha Agung",
    "content_ru": "Я прошу прощения у Всемогущего Аллаха",
    "content_ur": "میں اللہ کی مغفرت طلب کرتا ہوں",
    "content_zh-rCN": "我寻求万能的真主的宽恕",
    "content_bn": "আমি সর্বশক্তিমান আল্লাহর ক্ষমা প্রার্থনা করছি",
    "content_hi": "I seek the forgiveness of Allah the Almighty",
    "content_tr": "Allah\\'tan af ve mağfiret dilerim",
    "content_fr": "Je cherche le pardon d\\'Allah le Tout-Puissant",
    "content_de": "Ich suche Vergebung bei Allah dem Allmächtigen"
  },
  {
    "transliteration": "La Hawla Wala Quwatta ila Billah",
    "audio_url": "http://zj-s.usicdn.com/muslim/res/tasbih/lahawla.mp3",
    "content_ar": "لَا حَوْلَ وَلَا قُوَّةَ إِلَّا بِالله",
    "default_count": 33,
    "order": 8,
    "content_en": "There is no power and no strength except with Allah",
    "content_ms": "Tiada daya dan tiadalah kuasa melainkan dengan Allah",
    "content_ru": "Нет силы и мощи ни у кого, кроме Аллаха",
    "content_ur": "اللہ کے سوا کوئی طاقت اور طاقت نہیں ہے",
    "content_zh-rCN": "There is no power and no strength except with Allah",
    "content_bn": "আল্লাহ ব্যতীত কোন ক্ষমতা ও শক্তি নেই",
    "content_hi": "There is no power and no strength except with Allah",
    "content_tr": "Güç ve kuvvet, sadece Yüce Allah’ın yardımıyla elde edilir",
    "content_fr": "Il n\\'y a de puissance et de force qu\\'avec Allah",
    "content_de": "Es gibt weder Macht noch Stärke als bei Allah"
  },
  {
    "transliteration": "Laa ilaaha illa anta subhaanaka innee kuntu minadh dhaalimeen",
    "audio_url": "http://zj-s.usicdn.com/muslim/res/tasbih/lailahaillaanta.mp3",
    "content_ar": "لَا إِلَهَ إِلَّا أَنْتَ سُبْحَانَكَ إِنِّيْ كُنْتُ مِنَ الظَّالِمِيْن",
    "default_count": 33,
    "order": 9,
    "content_en": "There is no deity except You, exalted are You. Indeed, I have been the wrongdoers",
    "content_ms": "Tiada tuhan melainkan Engkau, Maha Suci Engkau. Sesungguhnya aku dari orang-orang yang zalim",
    "content_ru": "Нет божества, кроме Тебя! Пречист Ты! Воистину, я был одним из беззаконников!",
    "content_ur": "تیرے سوا کوئی معبود نہیں ، بلند تم ہو۔ بے شک میں ظالم رہا ہوں",
    "content_zh-rCN": "There is no deity except You, exalted are You. Indeed, I have been the wrongdoers",
    "content_bn": "আপনি ব্যাতিত কোনো মা\\'বুদ্ নেই, আপনিই সর্বমহান। অবশ্যই আমি গুনাহগার",
    "content_hi": "There is no deity except You, exalted are You. Indeed, I have been the wrongdoers",
    "content_tr": "Senden başka ilâh yoktur. Sen her türlü noksanlıktan, eşi-ortağı olmaktan uzaksın. Şüphesiz ben kendine yazık edenlerden oldum",
    "content_fr": "Il n\\'y a de divinité que toi, exalté es-tu. En effet, j\\'ai été le fautif",
    "content_de": "Es gibt keine Gottheit außer dir, erhaben bist du. Möge Allah uns vergeben."
  },
  {
    "transliteration": "A'udhu bi kalimaa tillahittammati min sharri maa khalaq",
    "audio_url": "http://zj-s.usicdn.com/muslim/res/tasbih/audhubikalimaa.mp3",
    "content_ar": "أَعُوْذُ بِكَلِمَاتِ اللهِ التَّامَّاتِ مِنْ شَرِّ مَا خَلَق",
    "default_count": 33,
    "order": 10,
    "content_en": "I seek refuge in Allah\\'s words from the evil of what He has created",
    "content_ms": "Aku berlindung dengan kalimah Allah dari kejahatan yang Dia ciptakan",
    "content_ru": "Прибегаю к защите совершенных слов Аллаха от зла того, что Он создал",
    "content_ur": "میں اللہ کی باتوں سے اس کی برائی سے پناہ مانگتا ہوں",
    "content_zh-rCN": "我在真主的话语中寻求庇护以逃避他所创造的邪恶",
    "content_bn": "আমি অভিশপ্ত শয়তান থেকে আল্লাহর আশ্রয় প্রার্থনা করি",
    "content_hi": "I seek refuge in Allah\\'s words from the evil of what He has created",
    "content_tr": "Allah\\'ın yarattığı kötülükten Allah\\'ın sözlerine sığınırım",
    "content_fr": "Je cherche refuge dans les paroles d\\'Allah contre le mal de ce qu\\'Il a créé",
    "content_de": "Ich suche Zuflucht in Allahs Worten, Zuflucht vor dem Bösen dessen, was Er geschaffen hat."
  },
  {
    "transliteration": "Allahumma Salli ‘Ala Muhammadin Wa ‘Ala Aali Muhammad",
    "content_ar": "اَللَّهُمَّ صَلِّ عَلَى مُحَمَّدٍ وَّعَلَى آلِ مُحَمَّدٍ",
    "default_count": 33,
    "order": 11,
    "content_en": "O Allah, send blessings upon Muhammad and the Progeny of Muhammad.",
    "content_ms": "Ya Allah, selawat dan salam ke atas Rasulullah Muhammad S.A.W dan Ahli keluarga Rasulullah Muhammad S.A.W.",
    "content_ru": "О Аллах, благослови Мухаммада и семейство Мухаммада.",
    "content_ur": "اے اللہ ، محمد صلی اللہ علیہ وسلم اور آل محمد کی اولاد پر درود بھیج۔",
    "content_zh-rCN": "O Allah, send blessings upon Muhammad and the Progeny of Muhammad.",
    "content_bn": "হে আল্লাহ, মুহাম্মাদ ও মুহাম্মাদ এর পরিবারকে রহমত করুন।",
    "content_hi": "O Allah, send blessings upon Muhammad and the Progeny of Muhammad.",
    "content_tr": "Allah\\'ım! Muhammed\\'e ve Muhammed\\'in ümmetine rahmet eyle.",
    "content_fr": "O Allah, envoie tes bénédictions sur Muhammad et sur la progéniture de Muhammad.",
    "content_de": "O Allah, sende deinen Segen an Mohammed und die Nachkommen Mohammeds."
  },
  {
    "transliteration": "Allahumma Salli ‘Ala Muhammadin Wa ‘Ala Aali Muhammad, Kama Sollaita ‘Ala Aali Ibraahim   Wa 'Ala Aali Ibrahim, Wa Baarik 'Ala Muhammadin Wa ‘Ala Aali Muhammad, Kama Baarakta ‘Ala Aali Ibraahim Wa 'Ala 'Aali Ibrahim, fil alamin Innaka Hamiidun Majid  ",
    "content_ar": "اَللَّهُمَّ صَلِّ عَلَى مُحَمَّدٍ وَّعَلَى آلِ مُحَمَّدٍ كَمَـا صَلَّيْتَ عَلَى اِبْرَاهِيْمَ وَعَلَى آلِ اِبْرَاهِيْمَ اِنَّكَ حَمِيْدٌمَّجِيْدٌ اَللَّهُمَّ بَـارِكْ عَلَى مُحَمَّدٍ وَّعَلَى آلِ مُحَمَّدٍ كَمَـا بَـاَرَكْتَ عَلَى اِبْرَاهِيْمَ وَعَلَى آلِ اِبْرَاهِيْمَ اِنَّكَ حَمِيْدٌ مَّجِيْدٌ",
    "default_count": 33,
    "order": 12,
    "content_en": "O Allah, bless Muhammad and the family of Muhammad as You blessed Ibrahim and the family of Ibrahim. You are the Most Praiseworthy. O Allah, bless Muhammad and the family of Muhammad as You blessed Ibrahim and the family of Ibrahim, verily You are the Most Praiseworthy, the Most Glorious.",
    "content_ms": "Ya Allah, berilah selawat kepada Muhammad dan keluarga Muhammad, seperti selawat-Mu kepada Ibrahim, dan berilah keberkatan kepada Muhammad dan keluarga Muhammad, seperti keberkatan-Mu kepada keluarga Ibrahim, di seluruh alam, sesungguhnya Engkaulah Maha Terpuji lagi Maha Mulia.",
    "content_ru": "О Аллах, благослови Мухаммада и его семейство, как Ты благословил Ибрахима и семейство Ибрахима, поистине, Ты – Достойный похвалы. Славный! О, Аллах, пошли Мухаммаду и его семейству благословения, как послал Ты их Ибрахиму и семейству Ибрахима. Поистине, Ты – Достойный похвалы, Славный!",
    "content_ur": "اے اللہ ، محمد کو اور آل کے خاندان کو بھی اسی طرح برکت دو جس طرح تو نے ابراہیم کو اور آل ابراہیم کو برکت دی۔ آپ سب سے زیادہ قابل ستائش ہیں۔ اے اللہ ، محمد کو اور آل کے گھر والوں کو بھی برکت دو جس طرح تو نے ابراہیم کو اور آل ابراہیم کو برکت دی ، بیشک تم سب سے زیادہ قابل ستائش اور قابل ستائش ہو۔",
    "content_zh-rCN": "O Allah, bless Muhammad and the family of Muhammad as You blessed Ibrahim and the family of Ibrahim. You are the Most Praiseworthy. O Allah, bless Muhammad and the family of Muhammad as You blessed Ibrahim and the family of Ibrahim, verily You are the Most Praiseworthy, the Most Glorious.",
    "content_bn": "হে আল্লাহ, মুহাম্মাদ ও মুহাম্মাদ এর পরিবারকে রহমত করুন, যেমন আপনি ইব্রাহিম ও তাঁর পরিবারকে রহমত করেছেন। নিশ্চয়ই আপনি প্রশংসনীয়। হে আল্লাহ, মুহাম্মাদ ও মুহাম্মাদ এর পরিবারকে রহমত করুন, যেমন আপনি ইব্রাহিম ও তাঁর পরিবারকে রহমত করেছেন। নিশ্চয়ই আপনি প্রশংসনীয় ও মহিমান্বিত।",
    "content_hi": "O Allah, bless Muhammad and the family of Muhammad as You blessed Ibrahim and the family of Ibrahim. You are the Most Praiseworthy. O Allah, bless Muhammad and the family of Muhammad as You blessed Ibrahim and the family of Ibrahim, verily You are the Most Praiseworthy, the Most Glorious.",
    "content_tr": "Allah\\'ım! Muhammed\\'e ve Muhammed\\'in ümmetine rahmet eyle; şerefini yücelt. İbrahim\\'e ve İbrahim\\'in ümmetine rahmet ettiğin gibi. Şüphesiz övülmeye layık yalnız sensin, şan ve şeref sahibi de sensin.",
    "content_fr": "O Allah, bénis Muhammad et la famille de Muhammad comme Tu as béni Ibrahim et la famille d\\'Ibrahim. Vous êtes le plus digne d\\'éloges. O Allah, bénis Muhammad et la famille de Muhammad comme tu as béni Ibrahim et la famille d\\'Ibrahim, en vérité tu es le plus louable, le plus glorieux.",
    "content_de": "O Allah, segne Muhammad und die Familie von Muhammad, wie du Ibrahim und die Familie von Ibrahim gesegnet hast. Du bist der Lobenswerteste. O Allah, segne Muhammad und die Familie von Muhammad, wie du Ibrahim und die Familie von Ibrahim gesegnet hast, wahrlich, du bist der Lobenswerteste, der Herrlichste."
  },
  {
    "transliteration": "Allahumma antas salaam, waminkas salaam, wa ilaika ya’udus salaam. Tabarakta ya dhal jalaali wal Ikram.",
    "content_ar": "اللَّهُمَّ أَنْتَ السَّلاَمُ وَمِنْكَ السَّلاَمُ تَبَارَكْتَ يَا ذَا الْجَلاَلِ وَالإِكْرَامِ",
    "default_count": 33,
    "order": 13,
    "content_en": "O Allah, You are As-Salaam (Who gives salvation), from You is salvation, and blessings from You, the Most Great and the Most Glorious.",
    "content_ms": "“Ya Allah, Engkau adalah Zat yang mempunyai kesejahteraan dan dari-Mu kesejahteraan itu kepada-Mu akan kembali lagi segala kesejahteraan itu. Engkaulah yang berkuasa memberi berkah yang banyak dan Engkaulah Yang Maha Tinggi, wahai Zat yang memiliki keagungan dan kemuliaan.”",
    "content_ru": "О Аллах! Ты - мир, и от Тебя — мир. Благословен Ты, о Обладающий величием и великодушием.",
    "content_ur": "اے اللہ ، آپ سلام ہیں ، جو آپ کی طرف سے نجات ہے ، اور آپ کی طرف سے سب سے بڑا اور عظیم الشان رحمت ہے۔",
    "content_zh-rCN": "O Allah, You are As-Salaam (Who gives salvation), from You is salvation, and blessings from You, the Most Great and the Most Glorious.",
    "content_bn": "হে আল্লাহ আপনি শান্তিময়, আপনার থেকে ই আসে শান্তি, আপনি বরকতময় হে পরাক্রমশালী ও মর্যাদাশীল সত্তা।",
    "content_hi": "O Allah, You are As-Salaam (Who gives salvation), from You is salvation, and blessings from You, the Most Great and the Most Glorious.",
    "content_tr": "Allah\\'ım sen selamsın. Selamet de sendendir. Ey celâl ve ikrâm sâhibi sen münezzehsin, sen yücesin",
    "content_fr": "O Allah, tu es As-Salaam (qui donne le salut), de toi est le salut, et les bénédictions de toi, le plus grand et le plus glorieux",
    "content_de": "O Allah, du bist As-Salaam (der das Heil gibt), von dir ist kommt Heil und Segen, mein Herr und Schöpfer."
  },
  {
    "transliteration": "Ya hayyu ya qayyum bi rahmatika astaghiitsu, wa ash-lihlii sya’nii kullahu wa laa takilnii ilaa nafsii thorfata ‘ainin abadan",
    "content_ar": "يا حَيُّ يَا قَيُّوْمُ بِرَحْمَتِكَ أَسْتَغِيْثُ، أَصْلِحْ لِيْ شَأْنِيْ كُلَّهُ وَلاَ تَكِلْنِيْ إِلَى نَفْسِيْ طَرْفَةَ عَيْنٍ أَبَدًا",
    "default_count": 33,
    "order": 14,
    "content_en": "O God Almighty, O God who stands alone, by Your mercy I ask for help, improve all my affairs and do not leave it to me for a moment (without getting help from You)",
    "content_ms": "Ya Tuhan Yang Maha Berkuasa, Ya Tuhan y[\n  {\n    \"transliteration\": \"Allahu Akbar\",\n    \"audio_url\": \"http://zj-s.usicdn.com/muslim/res/tasbih/allahuakbar.mp3\",\n    \"content_ar\": \"اللهُ أَكْبَرْ\",\n    \"default_count\": 33,\n    \"order\": 1,\n    \"content_en\": \"Allah is The Greatest\",\n    \"content_ms\": \"Allah Maha Besar\",\n    \"content_ru\": \"Аллаху Акбар\",\n    \"content_ur\": \"اللّه سب سے بڑا ہےالله سب سے بڑا ہے\",\n    \"content_zh-rCN\": \"真主至大\",\n    \"content_bn\": \"আল্লাহ সর্বশ্রেষ্ঠ\",\n    \"content_hi\": \"Allah is The Greatest\",\n    \"content_tr\": \"Allah en Büyüktür\",\n    \"content_fr\": \"Allah est le plus grand\",\n    \"content_de\": \"Allah ist der Beste.\"\n  },\n  {\n    \"transliteration\": \"Alhamdulillah\",\n    \"audio_url\": \"http://zj-s.usicdn.com/muslim/res/tasbih/alhamdulillah.mp3\",\n    \"content_ar\": \"اَلْحَمْدُ لِله\",\n    \"default_count\": 33,\n    \"order\": 2,\n    \"content_en\": \"Praise be to Allah\",\n    \"content_ms\": \"Segala puji bagi Allah\",\n    \"content_ru\": \"Хвала Аллаху\",\n    \"content_ur\": \"تمام تعریف اللہ کے لیے.\",\n    \"content_zh-rCN\": \"赞颂全归真主\",\n    \"content_bn\": \"সমস্ত প্রশংসা মহান আল্লাহর\",\n    \"content_hi\": \"Praise be to Allah\",\n    \"content_tr\": \"Hamd Allah\\\\'a mahsustur\",\n    \"content_fr\": \"Louange à Allah\",\n    \"content_de\": \"Mein Lob und meine Verehrung dem Herrn\"\n  },\n  {\n    \"transliteration\": \"Subhan Allah\",\n    \"audio_url\": \"http://zj-s.usicdn.com/muslim/res/tasbih/subhanallah.mp3\",\n    \"content_ar\": \"سبحان الله\",\n    \"default_count\": 33,\n    \"order\": 3,\n    \"content_en\": \"Glory be to Allah\",\n    \"content_ms\": \"Maha suci Allah\",\n    \"content_ru\": \"Слава Аллаху\",\n    \"content_ur\": \"سبحان اللہ\",\n    \"content_zh-rCN\": \"愿荣耀归真主阿拉\",\n    \"content_bn\": \"মহিমা আল্লাহর জন্য\",\n    \"content_hi\": \"सुभान अल्लाह\",\n    \"content_tr\": \"Allah\\\\'a şükürler olsun\",\n    \"content_fr\": \"Gloire à Allah\",\n    \"content_de\": \"Gepriesen sei Allah\"\n  },\n  {\n    \"transliteration\": \"Subhan Allahi wa bi Hamdihi, Subhan Allahil Adhim\",\n    \"audio_url\": \"http://zj-s.usicdn.com/muslim/res/tasbih/subhanallahi_long.mp3\",\n    \"content_ar\": \"سُبْحَانَ اللهِ وَ بِحَمْدِهِ, سُبْحَانَ اللهِ الْعَظِيْم\",\n    \"default_count\": 33,\n    \"order\": 4,\n    \"content_en\": \"Allah is free from imperfections and all praise is due to Him, Allah is The Greatest\",\n    \"content_ms\": \"Mahasuci Allah dan segala puji bagi-Nya. Mahasuci Allah yang Maha agung\",\n    \"content_ru\": \"Пречист Аллах, хвала Ему, Пречист Аллах Всевышний\",\n    \"content_ur\": \"ذکر_ترجمان_سوبناللہاہی_لگ \\\\\\\"سبحان الٰہی و دو ہمدیہی ، سبحان اللہ العظیم\\\\\\\" کا ترجمہ ، جو آپ کی زبان کے لئے بڑے پیمانے پر استعمال ہوتا ہے اسے استعمال کرنا بہتر ہوگا.\",\n    \"content_zh-rCN\": \"Allah is free from imperfections and all praise is due to Him, Allah is The Greatest\",\n    \"content_bn\": \"মহান আল্লাহ সকল ত্রুটির উর্দ্ধে, এবং সমস্ত প্রশংসা তার, অবশ্যই আল্লাহ সর্বশ্রেষ্ঠ\",\n    \"content_hi\": \"Allah is free from imperfections and all praise is due to Him, Allah is The Greatest\",\n    \"content_tr\": \"Allah noksanlardan münezzehtir, Allah en Büyüktür\",\n    \"content_fr\": \"Allah est exempt d\\\\'imperfections et toute louange lui est due, Allah est le plus grand\",\n    \"content_de\": \"Allah ist frei von Fehlern und jeder lob ist wegen ihm, Allah ist der Beste.\"\n  },\n  {\n    \"transliteration\": \"La ilaha illa Allah\",\n    \"audio_url\": \"http://zj-s.usicdn.com/muslim/res/tasbih/lailahaillallah.mp3\",\n    \"content_ar\": \"لَا إِلَهَ إِلَّا الله\",\n    \"default_count\": 33,\n    \"order\": 5,\n    \"content_en\": \"There is no god except Allah\",\n    \"content_ms\": \"Tiada tuhan melainkan Allah\",\n    \"content_ru\": \"Нет божества достойного поклонения, помимо Аллаха\",\n    \"content_ur\": \"اللہ کے سوا کوئی معبود نہیں\",\n    \"content_zh-rCN\": \"除真主外，没有其他神灵\",\n    \"content_bn\": \"আল্লাহ ছাড়া কোনো মা\\\\'বুদ্ নেই\",\n    \"content_hi\": \"There is no god except Allah\",\n    \"content_tr\": \"Allah\\\\'tan başka ilah yoktur\",\n    \"content_fr\": \"Il n\\\\'y a pas de dieu sauf Allah\",\n    \"content_de\": \"Es gibt keinen Gott außer Gott\"\n  },\n  {\n    \"transliteration\": \"Astagfirullah\",\n    \"audio_url\": \"http://zj-s.usicdn.com/muslim/res/tasbih/astagfirullah.mp3\",\n    \"content_ar\": \"أَسْتَغْفِرُ الله\",\n    \"default_count\": 33,\n    \"order\": 6,\n    \"content_en\": \"I seek Allah\\\\'s forgiveness\",\n    \"content_ms\": \"Aku memohon keampunan Allah\",\n    \"content_ru\": \"Я прошу прощения у Аллаха\",\n    \"content_ur\": \"میں اللہ کی مغفرت طلب کرتا ہوں\",\n    \"content_zh-rCN\": \"愿主恕饶\",\n    \"content_bn\": \"আমি আল্লাহর ক্ষমা প্রার্থনা করছি\",\n    \"content_hi\": \"I seek Allah\\\\'s forgiveness\",\n    \"content_tr\": \"Allah\\\\'tan af dilerim\",\n    \"content_fr\": \"Je cherche le pardon d\\\\'Allah\",\n    \"content_de\": \"Ich bitte um Allahs Vergebung\"\n  },\n  {\n    \"transliteration\": \"Astagfirullahal 'azeem\",\n    \"audio_url\": \"http://zj-s.usicdn.com/muslim/res/tasbih/astagfirullah_long.mp3\",\n    \"content_ar\": \"أَسْتَغْفِرُ اللهَ الْعَظِيْم\",\n    \"default_count\": 33,\n    \"order\": 7,\n    \"content_en\": \"I seek the forgiveness of Allah the Almighty\",\n    \"content_ms\": \"Aku mohon ampunan kepada Allah Yang Maha Agung\",\n    \"content_ru\": \"Я прошу прощения у Всемогущего Аллаха\",\n    \"content_ur\": \"میں اللہ کی مغفرت طلب کرتا ہوں\",\n    \"content_zh-rCN\": \"我寻求万能的真主的宽恕\",\n    \"content_bn\": \"আমি সর্বশক্তিমান আল্লাহর ক্ষমা প্রার্থনা করছি\",\n    \"content_hi\": \"I seek the forgiveness of Allah the Almighty\",\n    \"content_tr\": \"Allah\\\\'tan af ve mağfiret dilerim\",\n    \"content_fr\": \"Je cherche le pardon d\\\\'Allah le Tout-Puissant\",\n    \"content_de\": \"Ich suche Vergebung bei Allah dem Allmächtigen\"\n  },\n  {\n    \"transliteration\": \"La Hawla Wala Quwatta ila Billah\",\n    \"audio_url\": \"http://zj-s.usicdn.com/muslim/res/tasbih/lahawla.mp3\",\n    \"content_ar\": \"لَا حَوْلَ وَلَا قُوَّةَ إِلَّا بِالله\",\n    \"default_count\": 33,\n    \"order\": 8,\n    \"content_en\": \"There is no power and no strength except with Allah\",\n    \"content_ms\": \"Tiada daya dan tiadalah kuasa melainkan dengan Allah\",\n    \"content_ru\": \"Нет силы и мощи ни у кого, кроме Аллаха\",\n    \"content_ur\": \"اللہ کے سوا کوئی طاقت اور طاقت نہیں ہے\",\n    \"content_zh-rCN\": \"There is no power and no strength except with Allah\",\n    \"content_bn\": \"আল্লাহ ব্যতীত কোন ক্ষমতা ও শক্তি নেই\",\n    \"content_hi\": \"There is no power and no strength except with Allah\",\n    \"content_tr\": \"Güç ve kuvvet, sadece Yüce Allah’ın yardımıyla elde edilir\",\n    \"content_fr\": \"Il n\\\\'y a de puissance et de force qu\\\\'avec Allah\",\n    \"content_de\": \"Es gibt weder Macht noch Stärke als bei Allah\"\n  },\n  {\n    \"transliteration\": \"Laa ilaaha illa anta subhaanaka innee kuntu minadh dhaalimeen\",\n    \"audio_url\": \"http://zj-s.usicdn.com/muslim/res/tasbih/lailahaillaanta.mp3\",\n    \"content_ar\": \"لَا إِلَهَ إِلَّا أَنْتَ سُبْحَانَكَ إِنِّيْ كُنْتُ مِنَ الظَّالِمِيْن\",\n    \"default_count\": 33,\n    \"order\": 9,\n    \"content_en\": \"There is no deity except You, exalted are You. Indeed, I have been the wrongdoers\",\n    \"content_ms\": \"Tiada tuhan melainkan Engkau, Maha Suci Engkau. Sesungguhnya aku dari orang-orang yang zalim\",\n    \"content_ru\": \"Нет божества, кроме Тебя! Пречист Ты! Воистину, я был одним из беззаконников!\",\n    \"content_ur\": \"تیرے سوا کوئی معبود نہیں ، بلند تم ہو۔ بے شک میں ظالم رہا ہوں\",\n    \"content_zh-rCN\": \"There is no deity except You, exalted are You. Indeed, I have been the wrongdoers\",\n    \"content_bn\": \"আপনি ব্যাতিত কোনো মা\\\\'বুদ্ নেই, আপনিই সর্বমহান। অবশ্যই আমি গুনাহগার\",\n    \"content_hi\": \"There is no deity except You, exalted are You. Indeed, I have been the wrongdoers\",\n    \"content_tr\": \"Senden başka ilâh yoktur. Sen her türlü noksanlıktan, eşi-ortağı olmaktan uzaksın. Şüphesiz ben kendine yazık edenlerden oldum\",\n    \"content_fr\": \"Il n\\\\'y a de divinité que toi, exalté es-tu. En effet, j\\\\'ai été le fautif\",\n    \"content_de\": \"Es gibt keine Gottheit außer dir, erhaben bist du. Möge Allah uns vergeben.\"\n  },\n  {\n    \"transliteration\": \"A'udhu bi kalimaa tillahittammati min sharri maa khalaq\",\n    \"audio_url\": \"http://zj-s.usicdn.com/muslim/res/tasbih/audhubikalimaa.mp3\",\n    \"content_ar\": \"أَعُوْذُ بِكَلِمَاتِ اللهِ التَّامَّاتِ مِنْ شَرِّ مَا خَلَق\",\n    \"default_count\": 33,\n    \"order\": 10,\n    \"content_en\": \"I seek refuge in Allah\\\\'s words from the evil of what He has created\",\n    \"content_ms\": \"Aku berlindung dengan kalimah Allah dari kejahatan yang Dia ciptakan\",\n    \"content_ru\": \"Прибегаю к защите совершенных слов Аллаха от зла того, что Он создал\",\n    \"content_ur\": \"میں اللہ کی باتوں سے اس کی برائی سے پناہ مانگتا ہوں\",\n    \"content_zh-rCN\": \"我在真主的话语中寻求庇护以逃避他所创造的邪恶\",\n    \"content_bn\": \"আমি অভিশপ্ত শয়তান থেকে আল্লাহর আশ্রয় প্রার্থনা করি\",\n    \"content_hi\": \"I seek refuge in Allah\\\\'s words from the evil of what He has created\",\n    \"content_tr\": \"Allah\\\\'ın yarattığı kötülükten Allah\\\\'ın sözlerine sığınırım\",\n    \"content_fr\": \"Je cherche refuge dans les paroles d\\\\'Allah contre le mal de ce qu\\\\'Il a créé\",\n    \"content_de\": \"Ich suche Zuflucht in Allahs Worten, Zuflucht vor dem Bösen dessen, was Er geschaffen hat.\"\n  },\n  {\n    \"transliteration\": \"Allahumma Salli ‘Ala Muhammadin Wa ‘Ala Aali Muhammad\",\n    \"content_ar\": \"اللهم صل على محمد وعلى آل محمد\",\n    \"default_count\": 33,\n    \"order\": 11,\n    \"content_en\": \"O Allah, send blessings upon Muhammad and the Progeny of Muhammad.\",\n    \"content_ms\": \"Ya Allah, selawat dan salam ke atas Rasulullah Muhammad S.A.W dan Ahli keluarga Rasulullah Muhammad S.A.W.\",\n    \"content_ru\": \"О Аллах, благослови Мухаммада и семейство Мухаммада.\",\n    \"content_ur\": \"اے اللہ ، محمد صلی اللہ علیہ وسلم اور آل محمد کی اولاد پر درود بھیج۔\",\n    \"content_zh-rCN\": \"O Allah, send blessings upon Muhammad and the Progeny of Muhammad.\",\n    \"content_bn\": \"হে আল্লাহ, মুহাম্মাদ ও মুহাম্মাদ এর পরিবারকে রহমত করুন।\",\n    \"content_hi\": \"O Allah, send blessings upon Muhammad and the Progeny of Muhammad.\",\n    \"content_tr\": \"Allah\\\\'ım! Muhammed\\\\'e ve Muhammed\\\\'in ümmetine rahmet eyle.\",\n    \"content_fr\": \"O Allah, envoie tes bénédictions sur Muhammad et sur la progéniture de Muhammad.\",\n    \"content_de\": \"O Allah, sende deinen Segen an Mohammed und die Nachkommen Mohammeds.\"\n  },\n  {\n    \"transliteration\": \"Allahumma Salli ‘Ala Muhammadin Wa ‘Ala Aali Muhammad, Kama Sollaita ‘Ala Aali Ibraahim   Wa 'Ala Aali Ibrahim, Wa Baarik 'Ala Muhammadin Wa ‘Ala Aali Muhammad, Kama Baarakta ‘Ala Aali Ibraahim Wa 'Ala 'Aali Ibrahim, fil alamin Innaka Hamiidun Majid  \",\n    \"content_ar\": \"اللهم صل على محمد وعلى آل محمد كما صليت على إبراهيم وعلى آل إبراهيم. إنك حميد مجيد. اللهم بارك على محمد وعلى آل محمد كما باركت على إبراهيم وعلى آل إبراهيم. في العالمين إنك حميد مجيد.\",\n    \"default_count\": 33,\n    \"order\": 12,\n    \"content_en\": \"O Allah, bless Muhammad and the family of Muhammad as You blessed Ibrahim and the family of Ibrahim. You are the Most Praiseworthy. O Allah, bless Muhammad and the family of Muhammad as You blessed Ibrahim and the family of Ibrahim, verily You are the Most Praiseworthy, the Most Glorious.\",\n    \"content_ms\": \"Ya Allah, berilah selawat kepada Muhammad dan keluarga Muhammad, seperti selawat-Mu kepada Ibrahim, dan berilah keberkatan kepada Muhammad dan keluarga Muhammad, seperti keberkatan-Mu kepada keluarga Ibrahim, di seluruh alam, sesungguhnya Engkaulah Maha Terpuji lagi Maha Mulia.\",\n    \"content_ru\": \"О Аллах, благослови Мухаммада и его семейство, как Ты благословил Ибрахима и семейство Ибрахима, поистине, Ты – Достойный похвалы. Славный! О, Аллах, пошли Мухаммаду и его семейству благословения, как послал Ты их Ибрахиму и семейству Ибрахима. Поистине, Ты – Достойный похвалы, Славный!\",\n    \"content_ur\": \"اے اللہ ، محمد کو اور آل کے خاندان کو بھی اسی طرح برکت دو جس طرح تو نے ابراہیم کو اور آل ابراہیم کو برکت دی۔ آپ سب سے زیادہ قابل ستائش ہیں۔ اے اللہ ، محمد کو اور آل کے گھر والوں کو بھی برکت دو جس طرح تو نے ابراہیم کو اور آل ابراہیم کو برکت دی ، بیشک تم سب سے زیادہ قابل ستائش اور قابل ستائش ہو۔\",\n    \"content_zh-rCN\": \"O Allah, bless Muhammad and the family of Muhammad as You blessed Ibrahim and the family of Ibrahim. You are the Most Praiseworthy. O Allah, bless Muhammad and the family of Muhammad as You blessed Ibrahim and the family of Ibrahim, verily You are the Most Praiseworthy, the Most Glorious.\",\n    \"content_bn\": \"হে আল্লাহ, মুহাম্মাদ ও মুহাম্মাদ এর পরিবারকে রহমত করুন, যেমন আপনি ইব্রাহিম ও তাঁর পরিবারকে রহমত করেছেন। নিশ্চয়ই আপনি প্রশংসনীয়। হে আল্লাহ, মুহাম্মাদ ও মুহাম্মাদ এর পরিবারকে রহমত করুন, যেমন আপনি ইব্রাহিম ও তাঁর পরিবারকে রহমত করেছেন। নিশ্চয়ই আপনি প্রশংসনীয় ও মহিমান্বিত।\",\n    \"content_hi\": \"O Allah, bless Muhammad and the family of Muhammad as You blessed Ibrahim and the family of Ibrahim. You are the Most Praiseworthy. O Allah, bless Muhammad and the family of Muhammad as You blessed Ibrahim and the family of Ibrahim, verily You are the Most Praiseworthy, the Most Glorious.\",\n    \"content_tr\": \"Allah\\\\'ım! Muhammed\\\\'e ve Muhammed\\\\'in ümmetine rahmet eyle; şerefini yücelt. İbrahim\\\\'e ve İbrahim\\\\'in ümmetine rahmet ettiğin gibi. Şüphesiz övülmeye layık yalnız sensin, şan ve şeref sahibi de sensin.\",\n    \"content_fr\": \"O Allah, bénis Muhammad et la famille de Muhammad comme Tu as béni Ibrahim et la famille d\\\\'Ibrahim. Vous êtes le plus digne d\\\\'éloges. O Allah, bénis Muhammad et la famille de Muhammad comme tu as béni Ibrahim et la famille d\\\\'Ibrahim, en vérité tu es le plus louable, le plus glorieux.\",\n    \"content_de\": \"O Allah, segne Muhammad und die Familie von Muhammad, wie du Ibrahim und die Familie von Ibrahim gesegnet hast. Du bist der Lobenswerteste. O Allah, segne Muhammad und die Familie von Muhammad, wie du Ibrahim und die Familie von Ibrahim gesegnet hast, wahrlich, du bist der Lobenswerteste, der Herrlichste.\"\n  },\n  {\n    \"transliteration\": \"Allahumma antas salaam, waminkas salaam, wa ilaika ya’udus salaam. Tabarakta ya dhal jalaali wal Ikram.\",\n    \"content_ar\": \"اللهم أنت السلام ومنك السلام تباركت يا ذا الجلال والإكرام\",\n    \"default_count\": 33,\n    \"order\": 13,\n    \"content_en\": \"O Allah, You are As-Salaam (Who gives salvation), from You is salvation, and blessings from You, the Most Great and the Most Glorious.\",\n    \"content_ms\": \"“Ya Allah, Engkau adalah Zat yang mempunyai kesejahteraan dan dari-Mu kesejahteraan itu kepada-Mu akan kembali lagi segala kesejahteraan itu. Engkaulah yang berkuasa memberi berkah yang banyak dan Engkaulah Yang Maha Tinggi, wahai Zat yang memiliki keagungan dan kemuliaan.”\",\n    \"content_ru\": \"О Аллах! Ты - мир, и от Тебя — мир. Благословен Ты, о Обладающий величием и великодушием.\",\n    \"content_ur\": \"اے اللہ ، آپ سلام ہیں ، جو آپ کی طرف سے نجات ہے ، اور آپ کی طرف سے سب سے بڑا اور عظیم الشان رحمت ہے۔\",\n    \"content_zh-rCN\": \"O Allah, You are As-Salaam (Who gives salvation), from You is salvation, and blessings from You, the Most Great and the Most Glorious.\",\n    \"content_bn\": \"হে আল্লাহ আপনি শান্তিময়, আপনার থেকে ই আসে শান্তি, আপনি বরকতময় হে পরাক্রমশালী ও মর্যাদাশীল সত্তা।\",\n    \"content_hi\": \"O Allah, You are As-Salaam (Who gives salvation), from You is salvation, and blessings from You, the Most Great and the Most Glorious.\",\n    \"content_tr\": \"Allah\\\\'ım sen selamsın. Selamet de sendendir. Ey celâl ve ikrâm sâhibi sen münezzehsin, sen yücesin\",\n    \"content_fr\": \"O Allah, tu es As-Salaam (qui donne le salut), de toi est le salut, et les bénédictions de toi, le plus grand et le plus glorieux\",\n    \"content_de\": \"O Allah, du bist As-Salaam (der das Heil gibt), von dir ist kommt Heil und Segen, mein Herr und Schöpfer.\"\n  },\n  {\n    \"transliteration\": \"Ya hayyu ya qayyum bi rahmatika astaghiitsu, wa ash-lihlii sya’nii kullahu wa laa takilnii ilaa nafsii thorfata ‘ainin abadan\",\n    \"content_ar\": \"يا حَيُّ يَا قَيُّوْمُ بِرَحْمَتِكَ أَسْتَغِيْثُ، أَصْلِحْ لِيْ شَأْنِيْ كُلَّهُ وَلاَ تَكِلْنِيْ إِلَى نَفْسِيْ طَرْفَةَ عَيْنٍ أَبَدًا\",\n    \"default_count\": 33,\n    \"order\": 14,\n    \"content_en\": \"O God Almighty, O God who stands alone, by Your mercy I ask for help, improve all my affairs and do not leave it to me for a moment (without getting help from You)\",\n    \"content_ms\": \"Ya Tuhan Yang Maha Berkuasa, Ya Tuhan yang berdiri dengan sendirinya, dengan rahmat-Mu aku meminta pertolongan, perbaiki semua urusanku dan jangan serahkan padaku walau sebentar (tanpa mendapat pertolongan dari-Mu)\",\n    \"content_ru\": \"О, Вечно живой, о Вечно сущий, прибегаю к Твоей милости, исправь мои дела и не оставляй меня без поддержки даже на мгновение\",\n    \"content_ur\": \"اے اللہ تعالٰی ، جو اکیلا کھڑا ہے ، تیری رحمت سے میں مدد کے لئے دعا گو ہوں ، اپنے تمام معاملات کو بہتر بنائے اور ایک لمحے کے لئے بھی اس پر مجھ پر نہ چھوڑوں (آپ کی مدد حاصل کیے بغیر)\",\n    \"content_zh-rCN\": \"O God Almighty, O God who stands alone, by Your mercy I ask for help, improve all my affairs and do not leave it to me for a moment (without getting help from You)\",\n    \"content_bn\": \"হে চিরঞ্জীব, হে চিরস্থায়ী! আমি আপনার রহমতের অসীলায় আপনার কাছে উদ্ধার কামনা করি, আপনি আমার সার্বিক অবস্থা সংশোধন করে দিন, আর আমাকে আমার নিজের কাছে নিমেষের জন্যও সোপর্দ করবেন না।\",\n    \"content_hi\": \"O God Almighty, O God who stands alone, by Your mercy I ask for help, improve all my affairs and do not leave it to me for a moment (without getting help from You)\",\n    \"content_tr\": \"Ey Yüce Allah, Ey tek başına duran Allah, rahmetinle yardım isterim, bütün işlerimi iyileştirir ve senden yardım almadan bir an bile bana bırakma.\",\n    \"content_fr\": \"Ô Dieu Tout-Puissant, Ô Dieu qui se tient seul, par Ta miséricorde je demande de l\\\\'aide, améliore toutes mes affaires et ne me la laisse pas un instant (sans obtenir l\\\\'aide de Toi)\",\n    \"content_de\": \"Oh allmächtiger Gott, oh Gott, der allein steht. Mein Herr, ich verlasse mich nicht auf meine guten Taten, allein Deine Barmherzigkeit ist mein Halt, Deine Zufriedenheit mein Streben, Deine Vergebung meine Hoffnung.\"\n  }\n]\nang berdiri dengan sendirinya, dengan rahmat-Mu aku meminta pertolongan, perbaiki semua urusanku dan jangan serahkan padaku walau sebentar (tanpa mendapat pertolongan dari-Mu)",
    "content_ru": "О, Вечно живой, о Вечно сущий, прибегаю к Твоей милости, исправь мои дела и не оставляй меня без поддержки даже на мгновение",
    "content_ur": "اے اللہ تعالٰی ، جو اکیلا کھڑا ہے ، تیری رحمت سے میں مدد کے لئے دعا گو ہوں ، اپنے تمام معاملات کو بہتر بنائے اور ایک لمحے کے لئے بھی اس پر مجھ پر نہ چھوڑوں (آپ کی مدد حاصل کیے بغیر)",
    "content_zh-rCN": "O God Almighty, O God who stands alone, by Your mercy I ask for help, improve all my affairs and do not leave it to me for a moment (without getting help from You)",
    "content_bn": "হে চিরঞ্জীব, হে চিরস্থায়ী! আমি আপনার রহমতের অসীলায় আপনার কাছে উদ্ধার কামনা করি, আপনি আমার সার্বিক অবস্থা সংশোধন করে দিন, আর আমাকে আমার নিজের কাছে নিমেষের জন্যও সোপর্দ করবেন না।",
    "content_hi": "O God Almighty, O God who stands alone, by Your mercy I ask for help, improve all my affairs and do not leave it to me for a moment (without getting help from You)",
    "content_tr": "Ey Yüce Allah, Ey tek başına duran Allah, rahmetinle yardım isterim, bütün işlerimi iyileştirir ve senden yardım almadan bir an bile bana bırakma.",
    "content_fr": "Ô Dieu Tout-Puissant, Ô Dieu qui se tient seul, par Ta miséricorde je demande de l\\'aide, améliore toutes mes affaires et ne me la laisse pas un instant (sans obtenir l\\'aide de Toi)",
    "content_de": "Oh allmächtiger Gott, oh Gott, der allein steht. Mein Herr, ich verlasse mich nicht auf meine guten Taten, allein Deine Barmherzigkeit ist mein Halt, Deine Zufriedenheit mein Streben, Deine Vergebung meine Hoffnung."
  }
]
